peony/__init__.py
peony/api.py
peony/client.py
peony/data_processing.py
peony/exceptions.py
peony/general.py
peony/iterators.py
peony/oauth.py
peony/oauth_dance.py
peony/requests.py
peony/stream.py
peony/utils.py
peony/commands/__init__.py
peony/commands/commands.py
peony/commands/event_handlers.py
peony/commands/event_types.py
peony/commands/tasks.py
peony/commands/utils.py
peony_twitter-2.1.2.dist-info/LICENSE
peony_twitter-2.1.2.dist-info/METADATA
peony_twitter-2.1.2.dist-info/WHEEL
peony_twitter-2.1.2.dist-info/top_level.txt
peony_twitter-2.1.2.dist-info/RECORD
