Metadata-Version: 2.1
Name: peony-twitter
Version: 2.1.2
Summary: An asynchronous Twitter API client for Python 3.6+
Home-page: https://github.com/odrling/peony-twitter
Author: Florian Badie
Author-email: florianbadie@gmail.com
License: MIT License
Keywords: twitter,asyncio,asynchronous
Platform: UNKNOWN
Requires-Python: >=3.6
License-File: LICENSE
Requires-Dist: aiohttp (<4.0,>=2.0)
Requires-Dist: async-timeout
Provides-Extra: aiofiles
Requires-Dist: aiofiles ; extra == 'aiofiles'
Provides-Extra: aiohttp
Requires-Dist: aiodns ; extra == 'aiohttp'
Requires-Dist: cchardet ; extra == 'aiohttp'
Provides-Extra: all
Requires-Dist: aiodns ; extra == 'all'
Requires-Dist: aiofiles ; extra == 'all'
Requires-Dist: cchardet ; extra == 'all'
Requires-Dist: python-magic ; extra == 'all'
Requires-Dist: python-magic-bin ; (platform_system == "Windows") and extra == 'all'
Provides-Extra: magic
Requires-Dist: python-magic ; extra == 'magic'
Requires-Dist: python-magic-bin ; (platform_system == "Windows") and extra == 'magic'
Provides-Extra: media
Requires-Dist: aiofiles ; extra == 'media'
Requires-Dist: python-magic ; extra == 'media'
Requires-Dist: python-magic-bin ; (platform_system == "Windows") and extra == 'media'
Provides-Extra: tests
Requires-Dist: pytest ; extra == 'tests'
